{"id": "gen9randombattle-2259958418", "format": "[Gen 9] Random Battle", "players": ["klopeoa", "Dada hobo dweeb"], "log": "|j|\u2606klopeoa\n|j|\u2606Dada hobo dweeb\n|t:|1733784322\n|gametype|singles\n|player|p1|klopeoa|266|1000\n|player|p2|Dada hobo dweeb|102|1000\n|teamsize|p1|6\n|teamsize|p2|6\n|gen|9\n|tier|[Gen 9] Random Battle\n|rated|\n|rule|Species Clause: Limit one of each Pok\u00e9mon\n|rule|HP Percentage Mod: HP is shown in percentages\n|rule|Sleep Clause Mod: Limit one foe put to sleep\n|rule|Illusion Level Mod: Illusion disguises the Pok\u00e9mon's true level\n|\n|t:|1733784322\n|start\n|switch|p1a: Gumshoos|Gumshoos, L95, F|321/321\n|switch|p2a: Vigoroth|Vigoroth, L85, F|275/275\n|turn|1\n|inactive|Battle timer is ON: inactive players will automatically lose when time's up. (requested by klopeoa)\n|\n|t:|1733784341\n|move|p2a: Vigoroth|Bulk Up|p2a: Vigoroth\n|-boost|p2a: Vigoroth|atk|1\n|-boost|p2a: Vigoroth|def|1\n|move|p1a: Gumshoos|Knock Off|p2a: Vigoroth\n|-damage|p2a: Vigoroth|205/275\n|-enditem|p2a: Vigoroth|Eviolite|[from] move: Knock Off|[of] p1a: Gumshoos\n|\n|upkeep\n|turn|2\n|\n|t:|1733784352\n|switch|p1a: Noctowl|Noctowl, L95, F|344/344\n|move|p2a: Vigoroth|Bulk Up|p2a: Vigoroth\n|-boost|p2a: Vigoroth|atk|1\n|-boost|p2a: Vigoroth|def|1\n|\n|upkeep\n|turn|3\n|\n|t:|1733784362\n|move|p2a: Vigoroth|Body Slam|p1a: Noctowl\n|-crit|p1a: Noctowl\n|-damage|p1a: Noctowl|8/344\n|move|p1a: Noctowl|Hurricane|p2a: Vigoroth\n|-damage|p2a: Vigoroth|9/275\n|-start|p2a: Vigoroth|confusion\n|\n|upkeep\n|turn|4\n|\n|t:|1733784373\n|-activate|p2a: Vigoroth|confusion\n|move|p2a: Vigoroth|Body Slam|p1a: Noctowl\n|-damage|p1a: Noctowl|0 fnt\n|faint|p1a: Noctowl\n|\n|upkeep\n|\n|t:|1733784383\n|switch|p1a: Sneasler|Sneasler, L74, F|240/240\n|turn|5\n|\n|t:|1733784390\n|move|p1a: Sneasler|U-turn|p2a: Vigoroth\n|-damage|p2a: Vigoroth|0 fnt\n|faint|p2a: Vigoroth\n|\n|t:|1733784396\n|switch|p1a: Glimmora|Glimmora, L75, M|248/248|[from] U-turn\n|-item|p1a: Glimmora|Air Balloon\n|\n|upkeep\n|\n|t:|1733784411\n|switch|p2a: Hoopa|Hoopa, L85|275/275\n|turn|6\n|\n|t:|1733784427\n|switch|p1a: Brute Bonnet|Brute Bonnet, L81|312/312\n|move|p2a: Hoopa|Psychic|p1a: Brute Bonnet\n|-immune|p1a: Brute Bonnet\n|\n|upkeep\n|turn|7\n|\n|t:|1733784446\n|switch|p2a: Diancie|Diancie, L82|216/216\n|move|p1a: Brute Bonnet|Spore|p2a: Diancie\n|-status|p2a: Diancie|slp|[from] move: Spore\n|\n|upkeep\n|turn|8\n|\n|t:|1733784455\n|move|p1a: Brute Bonnet|Seed Bomb|p2a: Diancie\n|-supereffective|p2a: Diancie\n|-damage|p2a: Diancie|90/216 slp\n|cant|p2a: Diancie|slp\n|\n|-heal|p2a: Diancie|103/216 slp|[from] item: Leftovers\n|upkeep\n|turn|9\n|-message|Dada hobo dweeb forfeited.\n|\n|win|klopeoa\n|raw|klopeoa's rating: 1045 &rarr; <strong>1074</strong><br />(+29 for winning)\n|raw|Dada hobo dweeb's rating: 1000 &rarr; <strong>1000</strong><br />(+0 for losing)\n|l|\u2606Dada hobo dweeb\n|player|p2|\n", "inputlog": ">version bfd83cad13791eb5a5a409923076391caf6fb4d4\n>start {\"formatid\":\"gen9randombattle\",\"seed\":[32300,10052,45435,7741],\"rated\":\"Rated battle\"}\n>player p1 {\"name\":\"klopeoa\",\"avatar\":\"266\",\"rating\":1000,\"seed\":[14552,63666,15808,48149]}\n>player p2 {\"name\":\"Dada hobo dweeb\",\"avatar\":\"102\",\"rating\":1000,\"seed\":[5605,8812,29678,21622]}\n>p1 move knockoff\n>p2 move bulkup\n>p1 switch 4\n>p2 move bulkup\n>p1 move hurricane\n>p2 move bodyslam\n>p1 move hypervoice\n>p2 move bodyslam\n>p1 switch 2\n>p1 move uturn\n>p2 move earthquake\n>p1 switch 3\n>p2 switch 5\n>p1 switch 6\n>p2 move psychic\n>p1 move spore\n>p2 switch 3\n>p1 move seedbomb\n>p2 move calmmind\n>forcelose p2", "uploadtime": 1733784467, "views": 1, "formatid": "gen9randombattle", "rating": 1000, "private": 0, "password": null}