{"id": "gen9randombattle-2260785965", "format": "[Gen 9] Random Battle", "players": ["ghostshafted", "kongfu27"], "log": "|j|\u2606ghostshafted\n|j|\u2606kongfu27\n|t:|1733891838\n|gametype|singles\n|player|p1|ghostshafted|1|1357\n|player|p2|kongfu27|1|1324\n|teamsize|p1|6\n|teamsize|p2|6\n|gen|9\n|tier|[Gen 9] Random Battle\n|rated|\n|rule|Species Clause: Limit one of each Pok\u00e9mon\n|rule|HP Percentage Mod: HP is shown in percentages\n|rule|Sleep Clause Mod: Limit one foe put to sleep\n|rule|Illusion Level Mod: Illusion disguises the Pok\u00e9mon's true level\n|\n|t:|1733891838\n|start\n|switch|p1a: Crawdaunt|Crawdaunt, L84, M|243/243\n|switch|p2a: Drednaw|Drednaw, L81, M|278/278\n|turn|1\n|\n|t:|1733891851\n|switch|p2a: Sableye|Sableye, L89, F|234/234\n|move|p1a: Crawdaunt|Dragon Dance|p1a: Crawdaunt\n|-boost|p1a: Crawdaunt|atk|1\n|-boost|p1a: Crawdaunt|spe|1\n|\n|upkeep\n|turn|2\n|\n|t:|1733891859\n|move|p2a: Sableye|Will-O-Wisp|p1a: Crawdaunt\n|-hint|Since gen 7, Dark is immune to Prankster moves.\n|-immune|p1a: Crawdaunt\n|move|p1a: Crawdaunt|Crabhammer|p2a: Sableye\n|-damage|p2a: Sableye|0 fnt\n|faint|p2a: Sableye\n|-damage|p1a: Crawdaunt|219/243|[from] item: Life Orb\n|\n|upkeep\n|c|\u2606ghostshafted|im dead\n|\n|t:|1733891873\n|switch|p2a: Gogoat|Gogoat, L88, F|360/360\n|turn|3\n|\n|t:|1733891891\n|move|p1a: Crawdaunt|Knock Off|p2a: Gogoat\n|-damage|p2a: Gogoat|0 fnt\n|-enditem|p2a: Gogoat|Leftovers|[from] move: Knock Off|[of] p1a: Crawdaunt\n|faint|p2a: Gogoat\n|-damage|p1a: Crawdaunt|195/243|[from] item: Life Orb\n|\n|upkeep\n|c|\u2606ghostshafted|wow\n|c|\u2606ghostshafted|i did not expect that to kil\n|\n|t:|1733891905\n|switch|p2a: Drednaw|Drednaw, L81, M|278/278\n|turn|4\n|\n|t:|1733891913\n|move|p1a: Crawdaunt|Knock Off|p2a: Drednaw\n|-damage|p2a: Drednaw|0 fnt\n|-enditem|p2a: Drednaw|White Herb|[from] move: Knock Off|[of] p1a: Crawdaunt\n|faint|p2a: Drednaw\n|-damage|p1a: Crawdaunt|171/243|[from] item: Life Orb\n|\n|upkeep\n|c|\u2606ghostshafted|oof\n|\n|t:|1733891919\n|switch|p2a: Sunflora|Sunflora, M|312/312\n|turn|5\n|\n|t:|1733891925\n|move|p1a: Crawdaunt|Knock Off|p2a: Sunflora\n|-damage|p2a: Sunflora|0 fnt\n|-enditem|p2a: Sunflora|Life Orb|[from] move: Knock Off|[of] p1a: Crawdaunt\n|faint|p2a: Sunflora\n|-damage|p1a: Crawdaunt|147/243|[from] item: Life Orb\n|\n|upkeep\n|\n|t:|1733891935\n|switch|p2a: Lunala|Lunala, L70|308/308\n|turn|6\n|\n|t:|1733891941\n|-terastallize|p2a: Lunala|Fairy\n|move|p1a: Crawdaunt|Knock Off|p2a: Lunala\n|-resisted|p2a: Lunala\n|-damage|p2a: Lunala|220/308\n|-enditem|p2a: Lunala|Leftovers|[from] move: Knock Off|[of] p1a: Crawdaunt\n|-damage|p1a: Crawdaunt|123/243|[from] item: Life Orb\n|move|p2a: Lunala|Moongeist Beam|p1a: Crawdaunt\n|-resisted|p1a: Crawdaunt\n|-damage|p1a: Crawdaunt|51/243\n|\n|upkeep\n|turn|7\n|c|\u2606ghostshafted|i mean\n|c|\u2606ghostshafted|dont you think\n|c|\u2606ghostshafted|you shoulda did that\n|c|\u2606ghostshafted|like 3 mons earlier\n|c|\u2606ghostshafted|lmfao\n|\n|t:|1733891967\n|move|p1a: Crawdaunt|Crabhammer|p2a: Lunala\n|-damage|p2a: Lunala|0 fnt\n|faint|p2a: Lunala\n|-damage|p1a: Crawdaunt|27/243|[from] item: Life Orb\n|\n|upkeep\n|\n|t:|1733891972\n|switch|p2a: Masquerain|Masquerain, L87, F|264/264\n|-ability|p2a: Masquerain|Intimidate|boost\n|-unboost|p1a: Crawdaunt|atk|1\n|turn|8\n|\n|t:|1733891978\n|move|p1a: Crawdaunt|Crabhammer|p2a: Masquerain\n|-crit|p2a: Masquerain\n|-damage|p2a: Masquerain|0 fnt\n|faint|p2a: Masquerain\n|-damage|p1a: Crawdaunt|3/243|[from] item: Life Orb\n|\n|win|ghostshafted\n|raw|ghostshafted's rating: 1357 &rarr; <strong>1375</strong><br />(+18 for winning)\n|raw|kongfu27's rating: 1324 &rarr; <strong>1306</strong><br />(-18 for losing)\n|c|\u2606ghostshafted|gg\n|l|\u2606kongfu27\n|player|p2|\n", "inputlog": ">version bfd83cad13791eb5a5a409923076391caf6fb4d4\n>start {\"formatid\":\"gen9randombattle\",\"seed\":[44731,65504,28582,22743],\"rated\":\"Rated battle\"}\n>player p1 {\"name\":\"ghostshafted\",\"avatar\":\"1\",\"rating\":1357,\"seed\":[33201,62738,9781,55811]}\n>player p2 {\"name\":\"kongfu27\",\"avatar\":\"1\",\"rating\":1324,\"seed\":[140,16522,17661,49996]}\n>p1 move dragondance\n>p2 switch 3\n>p1 move crabhammer\n>p2 move willowisp\n>chat \u2606ghostshafted|im dead\n>p2 switch 6\n>p1 move knockoff\n>p2 move hornleech\n>chat \u2606ghostshafted|wow\n>chat \u2606ghostshafted|i did not expect that to kil\n>p2 switch 3\n>p1 move knockoff\n>p2 move shellsmash\n>chat \u2606ghostshafted|oof\n>p2 switch 4\n>p1 move knockoff\n>p2 move solarbeam\n>p2 switch 2\n>p1 move knockoff\n>p2 move moongeistbeam terastallize\n>chat \u2606ghostshafted|i mean \n>chat \u2606ghostshafted|dont you think\n>chat \u2606ghostshafted|you shoulda did that \n>chat \u2606ghostshafted|like 3 mons earlier \n>chat \u2606ghostshafted|lmfao\n>p1 move crabhammer\n>p2 move moongeistbeam\n>p2 switch 5\n>p1 move crabhammer\n>p2 move bugbuzz", "uploadtime": 1733891993, "views": 14, "formatid": "gen9randombattle", "rating": 1306, "private": 0, "password": null}